rain_shell_scripter.py
rain_shell_scripter-1.4.1.dist-info/LICENSE
rain_shell_scripter-1.4.1.dist-info/METADATA
rain_shell_scripter-1.4.1.dist-info/WHEEL
rain_shell_scripter-1.4.1.dist-info/entry_points.txt
rain_shell_scripter-1.4.1.dist-info/top_level.txt
rain_shell_scripter-1.4.1.dist-info/RECORD
