Metadata-Version: 2.1
Name: rain-shell-scripter
Version: 1.4.1
Summary: 用Python加持Linux Shell脚本，编写CSV文件即可完美解决脚本中的返回值、数值运算、错误处理、流程控制难题~
Home-page: https://github.com/fifilyu/rain-shell-scripter
Author: Fifi Lyu
Author-email: fifilyu@gmail.com
License: MIT
Platform: Linux
Classifier: Intended Audience :: Developers
Classifier: License :: OSI Approved :: MIT License
Classifier: Operating System :: OS Independent
Classifier: Programming Language :: Python
Classifier: Programming Language :: Python :: 3
Classifier: Topic :: Software Development :: Libraries :: Python Modules
Requires-Dist: happy-python
